nonebot_plugin_random_ban/__init__.py
nonebot_plugin_random_ban-0.2.1.dist-info/LICENSE
nonebot_plugin_random_ban-0.2.1.dist-info/METADATA
nonebot_plugin_random_ban-0.2.1.dist-info/WHEEL
nonebot_plugin_random_ban-0.2.1.dist-info/RECORD
