Metadata-Version: 2.1
Name: nonebot-plugin-random-ban
Version: 0.2.1
Summary: 随机禁言一名群员或自己n分钟（n通过参入数字然后随机实现），简单粗暴。
Home-page: https://github.com/Ikaros-521/nonebot_plugin_random_ban
License: MIT
Author: Ikaros
Author-email: 327209194@qq.com
Requires-Python: >=3.8,<4.0
Classifier: License :: OSI Approved :: MIT License
Classifier: Programming Language :: Python :: 3
Classifier: Programming Language :: Python :: 3.8
Classifier: Programming Language :: Python :: 3.9
Classifier: Programming Language :: Python :: 3.10
Classifier: Programming Language :: Python :: 3.11
Requires-Dist: nonebot-adapter-onebot (>=2.1.3,<3.0.0)
Requires-Dist: nonebot2 (>=2.0.0b5,<3.0.0)
Project-URL: Documentation, https://github.com/Ikaros-521/nonebot_plugin_random_ban/blob/master/README.md
Project-URL: Repository, https://github.com/Ikaros-521/nonebot_plugin_random_ban
